jsonexpr
