Metadata-Version: 2.4
Name: jsonexpr
Version: 0.2.4
Summary: An expression language.
Home-page: https://github.com/markuskimius/jsonexpr
Author: Mark Kim
Author-email: markuskimius+py@gmail.com
License: Apache 2.0
Keywords: expression,language,json
Requires-Dist: getopts
Requires-Dist: wasmtime
Provides-Extra: faster
Requires-Dist: wasmer; extra == "faster"
Requires-Dist: wasmer_compiler_cranelift; extra == "faster"
Provides-Extra: fastest
Requires-Dist: wasmer; extra == "fastest"
Requires-Dist: wasmer_compiler_llvm; extra == "fastest"
Dynamic: author
Dynamic: author-email
Dynamic: description
Dynamic: description-content-type
Dynamic: home-page
Dynamic: keywords
Dynamic: license
Dynamic: provides-extra
Dynamic: requires-dist
Dynamic: summary
